{
  "id": 11,
  "name": "Season 1: Platinum Guild Challenger Trophy",
  "description": "Earned when the PvP season ends and your guild team's placement is 1st on the Guild Challenger League leaderboard.",
  "categories": [
    12
  ],
  "max_count": 250,
  "icon": "decorations/11/icon.png",
  "wikiTitle": "Season 1: Platinum Guild Challenger Trophy (Handiwork)",
  "original": {
    "width": 1500,
    "height": 1459,
    "source": "decorations/11/preview.jpg",
    "remoteSource": "https://wiki.guildwars2.com/images/a/ab/Season_1-_Platinum_Guild_Challenger_Trophy.jpg"
  },
  "history": [
    {
      "day": "2026-06-12",
      "type": "Image Update",
      "name": "Season 1: Platinum Guild Challenger Trophy"
    },
    {
      "day": "2026-06-11",
      "type": "Image Update",
      "name": "Season 1: Platinum Guild Challenger Trophy"
    },
    {
      "day": "2026-05-30",
      "type": "Image Update",
      "name": "Season 1: Platinum Guild Challenger Trophy"
    },
    {
      "day": "2026-05-26",
      "type": "Image Update",
      "name": "Season 1: Platinum Guild Challenger Trophy"
    },
    {
      "day": "2026-05-24",
      "type": "Image Update",
      "name": "Season 1: Platinum Guild Challenger Trophy"
    },
    {
      "day": "2026-05-19",
      "type": "Image Update",
      "name": "Season 1: Platinum Guild Challenger Trophy"
    },
    {
      "day": "2026-05-17",
      "type": "Image Update",
      "name": "Season 1: Platinum Guild Challenger Trophy"
    },
    {
      "day": "2026-05-16",
      "type": "Image Update",
      "name": "Season 1: Platinum Guild Challenger Trophy"
    },
    {
      "day": "2026-05-15",
      "type": "Image Update",
      "name": "Season 1: Platinum Guild Challenger Trophy"
    },
    {
      "day": "2026-05-14",
      "type": "Image Update",
      "name": "Season 1: Platinum Guild Challenger Trophy"
    },
    {
      "day": "2026-05-13",
      "type": "Image Update",
      "name": "Season 1: Platinum Guild Challenger Trophy"
    },
    {
      "day": "2026-05-12",
      "type": "Image Update",
      "name": "Season 1: Platinum Guild Challenger Trophy"
    },
    {
      "day": "2026-05-11",
      "type": "Image Update",
      "name": "Season 1: Platinum Guild Challenger Trophy"
    },
    {
      "day": "2026-05-07",
      "type": "Image Update",
      "name": "Season 1: Platinum Guild Challenger Trophy"
    },
    {
      "day": "2026-05-03",
      "type": "Image Update",
      "name": "Season 1: Platinum Guild Challenger Trophy"
    },
    {
      "day": "2026-05-02",
      "type": "Image Update",
      "name": "Season 1: Platinum Guild Challenger Trophy"
    },
    {
      "day": "2026-04-27",
      "type": "Image Update",
      "name": "Season 1: Platinum Guild Challenger Trophy"
    },
    {
      "day": "2026-04-26",
      "type": "Image Update",
      "name": "Season 1: Platinum Guild Challenger Trophy"
    },
    {
      "day": "2026-04-25",
      "type": "Image Update",
      "name": "Season 1: Platinum Guild Challenger Trophy"
    },
    {
      "day": "2026-04-23",
      "type": "Image Update",
      "name": "Season 1: Platinum Guild Challenger Trophy"
    },
    {
      "day": "2026-04-17",
      "type": "Image Update",
      "name": "Season 1: Platinum Guild Challenger Trophy"
    },
    {
      "day": "2026-04-15",
      "type": "Image Update",
      "name": "Season 1: Platinum Guild Challenger Trophy"
    },
    {
      "day": "2026-04-14",
      "type": "Image Update",
      "name": "Season 1: Platinum Guild Challenger Trophy"
    },
    {
      "day": "2026-04-10",
      "type": "Image Update",
      "name": "Season 1: Platinum Guild Challenger Trophy"
    },
    {
      "day": "2026-04-09",
      "type": "Image Update",
      "name": "Season 1: Platinum Guild Challenger Trophy"
    },
    {
      "day": "2025-06-18",
      "type": "New Item",
      "name": "Weapons and Traps"
    },
    {
      "day": "2025-06-09",
      "type": "New Item",
      "name": "Weapons and Traps"
    },
    {
      "day": "2025-06-03",
      "type": "New Item",
      "name": "Season 1: Platinum Guild Challenger Trophy"
    },
    {
      "day": "2025-03-08",
      "type": "New Item",
      "name": "Weapons and Traps"
    },
    {
      "day": "2025-01-09",
      "type": "New Item",
      "name": "Weapons and Traps"
    },
    {
      "day": "2024-12-21",
      "type": "New Item",
      "name": "Weapons and Traps"
    },
    {
      "day": "2024-12-17",
      "type": "New Item",
      "name": "Weapons and Traps"
    },
    {
      "day": "2024-12-15",
      "type": "New Item",
      "name": "Weapons and Traps"
    },
    {
      "day": "2024-11-08",
      "type": "New Item",
      "name": "Weapons and Traps"
    }
  ]
}
