{
  "id": 281,
  "name": "Zephyr Koi Lantern",
  "description": "Crafted with Homesteading Mastery.",
  "categories": [
    5,
    24
  ],
  "max_count": 250,
  "icon": "https://render.guildwars2.com/file/4E0F5D9CDE17A9B39AC0FE780C3E4C0E1C36DD04/2179622.png",
  "wikiTitle": "Zephyr Koi Lantern (Handiwork)",
  "thumbnail": {
    "source": "https://wiki.guildwars2.com/images/thumb/2/28/Zephyr_Koi_Lantern.jpg/40px-Zephyr_Koi_Lantern.jpg",
    "width": 40,
    "height": 50
  },
  "original": {
    "source": "https://wiki.guildwars2.com/images/2/28/Zephyr_Koi_Lantern.jpg",
    "width": 1152,
    "height": 1440
  },
  "recipe": {
    "rating": 150,
    "type": "Homestead Decoration",
    "source": "Recipe Sheet",
    "disciplines": "Handiworker",
    "name": "Zephyr Koi Lantern",
    "sheet": "Homestead Recipe Book: Four Winds, Volume 2",
    "id": 14878,
    "ingredients": [
      {
        "slot": 1,
        "quantity": 27,
        "item": "Refined Homestead Fiber"
      },
      {
        "slot": 2,
        "quantity": 11,
        "item": "Silk Scrap"
      },
      {
        "slot": 3,
        "quantity": 20,
        "item": "Small Scale"
      }
    ]
  }
}
