{
  "id": 306,
  "name": "Kodan Vanity",
  "description": "Crafted with Homesteading Mastery.",
  "categories": [
    19,
    3
  ],
  "max_count": 250,
  "icon": "decorations/306/icon.png",
  "wikiTitle": "Kodan Vanity",
  "original": {
    "width": 1110,
    "height": 1080,
    "source": "decorations/306/preview.jpg",
    "remoteSource": "https://wiki.guildwars2.com/images/4/4a/Kodan_Vanity.jpg"
  },
  "recipe": {
    "rating": 75,
    "type": "Homestead Decoration",
    "source": "automatic",
    "disciplines": "Handiworker",
    "id": 14713,
    "ingredients": [
      {
        "slot": 1,
        "quantity": 27,
        "item": "Refined Homestead Wood"
      },
      {
        "slot": 2,
        "quantity": 12,
        "item": "Cured Rugged Leather Square"
      },
      {
        "slot": 3,
        "quantity": 8,
        "item": "Lowland Pine Log"
      }
    ]
  }
}
