{
  "id": 379,
  "name": "Unimpressive King Frog",
  "description": "Crafted with Homesteading Mastery.",
  "categories": [
    22
  ],
  "max_count": 250,
  "icon": "https://render.guildwars2.com/file/FAA1EFF7EE7BD236FAE2FFFA3A0E32067A2F08D0/1418358.png",
  "wikiTitle": "Unimpressive King Frog (Handiwork)",
  "thumbnail": {
    "source": "https://wiki.guildwars2.com/images/thumb/0/0d/Unimpressive_King_Frog.jpg/50px-Unimpressive_King_Frog.jpg",
    "width": 50,
    "height": 36
  },
  "original": {
    "source": "https://wiki.guildwars2.com/images/0/0d/Unimpressive_King_Frog.jpg",
    "width": 1856,
    "height": 1331
  },
  "recipe": {
    "rating": 225,
    "type": "Homestead Decoration",
    "source": "recipe sheet",
    "disciplines": "Handiworker",
    "name": "Unimpressive King Frog",
    "sheet": "Homestead Recipe Book: Super Adventure Box, Volume 1",
    "id": 14769,
    "ingredients": [
      {
        "slot": 1,
        "quantity": 32,
        "item": "Refined Homestead Metal"
      },
      {
        "slot": 2,
        "quantity": 8,
        "item": "Bauble"
      },
      {
        "slot": 3,
        "quantity": 16,
        "item": "Silver Ingot"
      }
    ]
  }
}
