{
  "id": 385,
  "name": "Kodan Ivory Couch",
  "description": "Crafted with Homesteading Mastery.",
  "categories": [
    2,
    19
  ],
  "max_count": 250,
  "icon": "https://render.guildwars2.com/file/E0051B7F0AC90A4374510AC9B515FD6FA21B195F/3375008.png",
  "wikiTitle": "Kodan Ivory Couch",
  "thumbnail": {
    "source": "https://wiki.guildwars2.com/images/thumb/3/35/Kodan_Ivory_Couch.jpg/50px-Kodan_Ivory_Couch.jpg",
    "width": 50,
    "height": 39
  },
  "original": {
    "source": "https://wiki.guildwars2.com/images/3/35/Kodan_Ivory_Couch.jpg",
    "width": 1401,
    "height": 1080
  },
  "recipe": {
    "rating": 150,
    "type": "Homestead Decoration",
    "source": "automatic",
    "disciplines": "Handiworker",
    "id": 14681,
    "ingredients": [
      {
        "slot": 1,
        "quantity": 34,
        "item": "Refined Homestead Fiber"
      },
      {
        "slot": 2,
        "quantity": 15,
        "item": "Cotton Scrap"
      },
      {
        "slot": 3,
        "quantity": 20,
        "item": "Honey Flower"
      }
    ]
  }
}
