{
  "id": 517,
  "name": "Crooked Mushroom",
  "description": "Crafted with Homesteading Mastery.",
  "categories": [
    7
  ],
  "max_count": 250,
  "icon": "decorations/517/icon.png",
  "wikiTitle": "Crooked Mushroom (Handiwork)",
  "original": {
    "width": 948,
    "height": 1422,
    "source": "decorations/517/preview.jpg",
    "remoteSource": "https://wiki.guildwars2.com/images/4/46/Crooked_Mushroom.jpg"
  },
  "recipe": {
    "rating": 75,
    "type": "Homestead Decoration",
    "source": "Recipe Sheet",
    "disciplines": "Handiworker",
    "name": "Crooked Mushroom",
    "sheet": "Homestead Recipe Book: Plants, Volume 1",
    "id": 14344,
    "ingredients": [
      {
        "slot": 1,
        "quantity": 4,
        "item": "Refined Homestead Fiber"
      },
      {
        "slot": 2,
        "quantity": 2,
        "item": "Mordrem Fragment"
      },
      {
        "slot": 3,
        "quantity": 1,
        "item": "Giant Mushroom Spore"
      }
    ]
  }
}
