{
  "id": 62,
  "name": "Skewed Stairway (Left)",
  "description": "Crafted with Homesteading Mastery.",
  "categories": [
    1,
    25
  ],
  "max_count": 250,
  "icon": "decorations/62/icon.png",
  "wikiTitle": "Skewed Stairway (Left) (Handiwork)",
  "original": {
    "width": 783,
    "height": 920,
    "source": "decorations/62/preview.jpg",
    "remoteSource": "https://wiki.guildwars2.com/images/6/6d/Skewed_Stairway_%28Left%29.jpg"
  },
  "recipe": {
    "rating": 225,
    "type": "Homestead Decoration",
    "source": "sheet",
    "disciplines": "Handiworker",
    "name": "Skewed Stairway (Left)",
    "sheet": "Homestead Recipe Book: Halloween, Volume 7",
    "id": 14783,
    "ingredients": [
      {
        "slot": 1,
        "quantity": 32,
        "item": "Refined Homestead Metal"
      },
      {
        "slot": 2,
        "quantity": 30,
        "item": "Piece of Candy Corn"
      },
      {
        "slot": 3,
        "quantity": 8,
        "item": "Venom Sac"
      }
    ]
  }
}
