{
  "id": 658,
  "name": "Dragon Bash Firework Launcher",
  "description": "Crafted with Homesteading Mastery.",
  "categories": [
    23,
    11
  ],
  "max_count": 250,
  "icon": "decorations/658/icon.png",
  "wikiTitle": "Dragon Bash Firework Launcher (Handiwork)",
  "original": {
    "width": 1021,
    "height": 1440,
    "source": "decorations/658/preview.jpg",
    "remoteSource": "https://wiki.guildwars2.com/images/d/d7/Dragon_Bash_Firework_Launcher.jpg"
  },
  "recipe": {
    "rating": 225,
    "type": "Homestead Decoration",
    "source": "Recipe Sheet",
    "disciplines": "Handiworker",
    "name": "Dragon Bash Firework Launcher",
    "sheet": "Homestead Recipe Book: Dragon Bash, Volume 3",
    "id": 14392,
    "ingredients": [
      {
        "slot": 1,
        "quantity": 25,
        "item": "Refined Homestead Metal"
      },
      {
        "slot": 2,
        "quantity": 50,
        "item": "Volatile Magic"
      },
      {
        "slot": 3,
        "quantity": 10,
        "item": "Piece of Zhaitaffy"
      }
    ]
  },
  "history": [
    {
      "day": "2026-06-11",
      "type": "Image Update",
      "name": "Dragon Bash Firework Launcher"
    },
    {
      "day": "2026-06-11",
      "type": "Recipe Added",
      "name": "Dragon Bash Firework Launcher"
    },
    {
      "day": "2026-06-11",
      "type": "Recipe Updated",
      "name": "Dragon Bash Firework Launcher"
    },
    {
      "day": "2026-05-25",
      "type": "Image Update",
      "name": "Dragon Bash Firework Launcher"
    },
    {
      "day": "2026-05-25",
      "type": "Recipe Added",
      "name": "Dragon Bash Firework Launcher"
    },
    {
      "day": "2026-05-25",
      "type": "Recipe Updated",
      "name": "Dragon Bash Firework Launcher"
    },
    {
      "day": "2026-05-24",
      "type": "Image Update",
      "name": "Dragon Bash Firework Launcher"
    },
    {
      "day": "2026-05-24",
      "type": "Recipe Added",
      "name": "Dragon Bash Firework Launcher"
    },
    {
      "day": "2026-05-24",
      "type": "Recipe Updated",
      "name": "Dragon Bash Firework Launcher"
    },
    {
      "day": "2026-05-19",
      "type": "Image Update",
      "name": "Dragon Bash Firework Launcher"
    },
    {
      "day": "2026-05-19",
      "type": "Recipe Added",
      "name": "Dragon Bash Firework Launcher"
    },
    {
      "day": "2026-05-19",
      "type": "Recipe Updated",
      "name": "Dragon Bash Firework Launcher"
    },
    {
      "day": "2026-05-17",
      "type": "Image Update",
      "name": "Dragon Bash Firework Launcher"
    },
    {
      "day": "2026-05-17",
      "type": "Recipe Added",
      "name": "Dragon Bash Firework Launcher"
    },
    {
      "day": "2026-05-17",
      "type": "Recipe Updated",
      "name": "Dragon Bash Firework Launcher"
    },
    {
      "day": "2026-05-16",
      "type": "Image Update",
      "name": "Dragon Bash Firework Launcher"
    },
    {
      "day": "2026-05-16",
      "type": "Recipe Added",
      "name": "Dragon Bash Firework Launcher"
    },
    {
      "day": "2026-05-16",
      "type": "Recipe Updated",
      "name": "Dragon Bash Firework Launcher"
    },
    {
      "day": "2026-05-15",
      "type": "Image Update",
      "name": "Dragon Bash Firework Launcher"
    },
    {
      "day": "2026-05-15",
      "type": "Recipe Added",
      "name": "Dragon Bash Firework Launcher"
    },
    {
      "day": "2026-05-15",
      "type": "Recipe Updated",
      "name": "Dragon Bash Firework Launcher"
    },
    {
      "day": "2026-05-14",
      "type": "Image Update",
      "name": "Dragon Bash Firework Launcher"
    },
    {
      "day": "2026-05-14",
      "type": "Recipe Added",
      "name": "Dragon Bash Firework Launcher"
    },
    {
      "day": "2026-05-14",
      "type": "Recipe Updated",
      "name": "Dragon Bash Firework Launcher"
    },
    {
      "day": "2026-05-13",
      "type": "Image Update",
      "name": "Dragon Bash Firework Launcher"
    },
    {
      "day": "2026-05-13",
      "type": "Recipe Added",
      "name": "Dragon Bash Firework Launcher"
    },
    {
      "day": "2026-05-13",
      "type": "Recipe Updated",
      "name": "Dragon Bash Firework Launcher"
    },
    {
      "day": "2026-05-12",
      "type": "Image Update",
      "name": "Dragon Bash Firework Launcher"
    },
    {
      "day": "2026-05-12",
      "type": "Recipe Added",
      "name": "Dragon Bash Firework Launcher"
    },
    {
      "day": "2026-05-12",
      "type": "Recipe Updated",
      "name": "Dragon Bash Firework Launcher"
    },
    {
      "day": "2026-05-11",
      "type": "Image Update",
      "name": "Dragon Bash Firework Launcher"
    },
    {
      "day": "2026-05-11",
      "type": "Recipe Updated",
      "name": "Dragon Bash Firework Launcher"
    },
    {
      "day": "2026-05-03",
      "type": "Image Update",
      "name": "Dragon Bash Firework Launcher"
    },
    {
      "day": "2026-05-03",
      "type": "Recipe Added",
      "name": "Dragon Bash Firework Launcher"
    },
    {
      "day": "2026-05-03",
      "type": "Recipe Updated",
      "name": "Dragon Bash Firework Launcher"
    },
    {
      "day": "2026-05-02",
      "type": "Image Update",
      "name": "Dragon Bash Firework Launcher"
    },
    {
      "day": "2026-05-02",
      "type": "Recipe Added",
      "name": "Dragon Bash Firework Launcher"
    },
    {
      "day": "2026-05-02",
      "type": "Recipe Updated",
      "name": "Dragon Bash Firework Launcher"
    },
    {
      "day": "2026-04-29",
      "type": "Recipe Added",
      "name": "Dragon Bash Firework Launcher"
    },
    {
      "day": "2026-04-29",
      "type": "Recipe Updated",
      "name": "Dragon Bash Firework Launcher"
    },
    {
      "day": "2026-04-25",
      "type": "Image Update",
      "name": "Dragon Bash Firework Launcher"
    },
    {
      "day": "2026-04-25",
      "type": "Recipe Added",
      "name": "Dragon Bash Firework Launcher"
    },
    {
      "day": "2026-04-25",
      "type": "Recipe Updated",
      "name": "Dragon Bash Firework Launcher"
    },
    {
      "day": "2026-04-20",
      "type": "Image Update",
      "name": "Dragon Bash Firework Launcher"
    },
    {
      "day": "2026-04-20",
      "type": "Recipe Added",
      "name": "Dragon Bash Firework Launcher"
    },
    {
      "day": "2026-04-20",
      "type": "Recipe Updated",
      "name": "Dragon Bash Firework Launcher"
    },
    {
      "day": "2026-04-17",
      "type": "Image Update",
      "name": "Dragon Bash Firework Launcher"
    },
    {
      "day": "2026-04-17",
      "type": "Recipe Added",
      "name": "Dragon Bash Firework Launcher"
    },
    {
      "day": "2026-04-17",
      "type": "Recipe Updated",
      "name": "Dragon Bash Firework Launcher"
    },
    {
      "day": "2026-04-15",
      "type": "Image Update",
      "name": "Dragon Bash Firework Launcher"
    },
    {
      "day": "2026-04-15",
      "type": "Recipe Added",
      "name": "Dragon Bash Firework Launcher"
    },
    {
      "day": "2026-04-15",
      "type": "Recipe Updated",
      "name": "Dragon Bash Firework Launcher"
    },
    {
      "day": "2026-04-14",
      "type": "Image Update",
      "name": "Dragon Bash Firework Launcher"
    },
    {
      "day": "2026-04-14",
      "type": "Recipe Updated",
      "name": "Dragon Bash Firework Launcher"
    },
    {
      "day": "2026-04-13",
      "type": "Image Update",
      "name": "Dragon Bash Firework Launcher"
    },
    {
      "day": "2026-04-13",
      "type": "Recipe Updated",
      "name": "Dragon Bash Firework Launcher"
    },
    {
      "day": "2026-04-11",
      "type": "Image Update",
      "name": "Dragon Bash Firework Launcher"
    },
    {
      "day": "2026-04-11",
      "type": "Recipe Updated",
      "name": "Dragon Bash Firework Launcher"
    },
    {
      "day": "2026-04-10",
      "type": "Image Update",
      "name": "Dragon Bash Firework Launcher"
    },
    {
      "day": "2026-04-10",
      "type": "Recipe Updated",
      "name": "Dragon Bash Firework Launcher"
    },
    {
      "day": "2025-10-30",
      "type": "Item Update",
      "name": "Dragon Bash Firework Launcher",
      "changes": [
        {
          "field": "description",
          "before": "Crafted by scribes.",
          "after": "Crafted with Homesteading Mastery."
        },
        {
          "field": "categories",
          "detail": "Dragon Bash was added",
          "before": null,
          "after": 23
        },
        {
          "field": "categories",
          "detail": "Super Adventure Box was removed",
          "before": 22,
          "after": null
        }
      ]
    },
    {
      "day": "2025-08-16",
      "type": "Item Removed",
      "name": "Dragon Bash Firework Launcher"
    },
    {
      "day": "2025-08-16",
      "type": "New Item",
      "name": "Dragon Bash Firework Launcher"
    },
    {
      "day": "2025-06-11",
      "type": "Image Update",
      "name": "Dragon Bash Firework Launcher"
    },
    {
      "day": "2024-11-19",
      "type": "New Item",
      "name": "Dragon Bash Firework Launcher"
    }
  ],
  "removed": true
}
