{
  "id": 755,
  "name": "Spiral Elonian Windmill",
  "description": "Crafted with Homesteading Mastery.",
  "categories": [
    16,
    14
  ],
  "max_count": 250,
  "icon": "decorations/755/icon.png",
  "wikiTitle": "Spiral Elonian Windmill (Handiwork)",
  "original": {
    "width": 1241,
    "height": 1241,
    "source": "decorations/755/preview.jpg",
    "remoteSource": "https://wiki.guildwars2.com/images/4/4d/Spiral_Elonian_Windmill_top.jpg"
  },
  "recipe": {
    "rating": 300,
    "type": "Homestead Decoration",
    "source": "Recipe Sheet",
    "disciplines": "Handiworker",
    "name": "Spiral Elonian Windmill",
    "sheet": "Homestead Recipe Book: Misc. Items, Volume 3",
    "id": 14776,
    "ingredients": [
      {
        "slot": 1,
        "quantity": 36,
        "item": "Refined Homestead Fiber"
      },
      {
        "slot": 2,
        "quantity": 10,
        "item": "Trade Contract"
      },
      {
        "slot": 3,
        "quantity": 3,
        "item": "Pouch of Red Pigment"
      }
    ]
  }
}
