{
  "id": 758,
  "name": "Bronze Mursaat Overseer Trophy",
  "description": "Crafted with Homesteading Mastery.",
  "categories": [
    12
  ],
  "max_count": 250,
  "icon": "https://render.guildwars2.com/file/3F2C0098F99560B5BD3D4A22B69022AC3C31B81F/1634831.png",
  "wikiTitle": "Bronze Mursaat Overseer Trophy (Handiwork)",
  "thumbnail": {
    "source": "https://wiki.guildwars2.com/images/thumb/4/4d/Bronze_Mursaat_Overseer_Trophy.jpg/24px-Bronze_Mursaat_Overseer_Trophy.jpg",
    "width": 24,
    "height": 50
  },
  "original": {
    "source": "https://wiki.guildwars2.com/images/4/4d/Bronze_Mursaat_Overseer_Trophy.jpg",
    "width": 502,
    "height": 1025
  },
  "recipe": {
    "rating": 225,
    "type": "Homestead Decoration",
    "source": "Recipe Sheet",
    "disciplines": "Handiworker",
    "name": "Bronze Mursaat Overseer Trophy",
    "sheet": "Recipe: Bronze Mursaat Overseer Trophy",
    "id": 14685,
    "ingredients": [
      {
        "slot": 1,
        "quantity": 36,
        "item": "Refined Homestead Wood"
      },
      {
        "slot": 2,
        "quantity": 10,
        "item": "Magnetite Shard"
      },
      {
        "slot": 3,
        "quantity": 1,
        "item": "Recreation Room Floor Fragment"
      }
    ]
  }
}
