{
  "id": 76,
  "name": "Tyrian Globe",
  "description": "Crafted with Homesteading Mastery.",
  "categories": [
    4
  ],
  "max_count": 250,
  "icon": "https://render.guildwars2.com/file/7F5EF9096BF3B543B2A302A2ABD5309F05FB5B50/1227641.png",
  "wikiTitle": "Tyrian Globe (Handiwork)",
  "thumbnail": {
    "source": "https://wiki.guildwars2.com/images/thumb/8/8b/Tyrian_Globe.jpg/39px-Tyrian_Globe.jpg",
    "width": 39,
    "height": 50
  },
  "original": {
    "source": "https://wiki.guildwars2.com/images/8/8b/Tyrian_Globe.jpg",
    "width": 955,
    "height": 1208
  },
  "recipe": {
    "rating": 400,
    "type": "Homestead Decoration",
    "source": "Recipe Sheet",
    "disciplines": "Handiworker",
    "name": "Tyrian Globe",
    "sheet": "Homestead Recipe Book: Kryta, Volume 1",
    "id": 14647,
    "ingredients": [
      {
        "slot": 1,
        "quantity": 34,
        "item": "Refined Homestead Wood"
      },
      {
        "slot": 2,
        "quantity": 40,
        "item": "Piece of Mother-of-Pearl"
      },
      {
        "slot": 3,
        "quantity": 3000,
        "item": "Karma"
      }
    ]
  }
}
