{
  "id": 815,
  "name": "Silver Vale Guardian Trophy",
  "description": "Crafted with Homesteading Mastery.",
  "categories": [
    12
  ],
  "max_count": 250,
  "icon": "decorations/815/icon.png",
  "wikiTitle": "Silver Vale Guardian Trophy (Handiwork)",
  "original": {
    "width": 477,
    "height": 1047,
    "source": "decorations/815/preview.jpg",
    "remoteSource": "https://wiki.guildwars2.com/images/8/85/Silver_Vale_Guardian_Trophy.jpg"
  },
  "recipe": {
    "rating": 300,
    "type": "Homestead Decoration",
    "source": "Recipe Sheet",
    "disciplines": "Handiworker",
    "name": "Silver Vale Guardian Trophy",
    "sheet": "Recipe: Silver Vale Guardian Trophy",
    "id": 14576,
    "ingredients": [
      {
        "slot": 1,
        "quantity": 90,
        "item": "Refined Homestead Metal"
      },
      {
        "slot": 2,
        "quantity": 40,
        "item": "Magnetite Shard"
      },
      {
        "slot": 3,
        "quantity": 3,
        "item": "Vale Guardian Fragment"
      }
    ]
  }
}
