{
  "id": 998,
  "name": "Burlap Sack Pile",
  "description": "Crafted with Homesteading Mastery.\n\nRequires Guild Wars 2: Visions of Eternity.",
  "categories": [
    20,
    4
  ],
  "max_count": 250,
  "icon": "https://render.guildwars2.com/file/C86A3BF3932059BC22044CC762A74F6D6180E00A/3708852.png",
  "wikiTitle": "Burlap Sack Pile (Handiwork)",
  "thumbnail": {
    "source": "https://wiki.guildwars2.com/images/thumb/7/74/Burlap_Sack_Pile.jpg/50px-Burlap_Sack_Pile.jpg",
    "width": 50,
    "height": 42
  },
  "original": {
    "source": "https://wiki.guildwars2.com/images/7/74/Burlap_Sack_Pile.jpg",
    "width": 1141,
    "height": 968
  }
}
